[
    {
        "url": "https://github.com/LafeLabs/library/tree/main/video-library/video",
        "display": "video",
        "title": "",
        "author": "",
        "location": "",
        "loc call number": "",
        "worldcat number": "",
        "message": "",
        "notes": "",
        "description": "",
        "condition": "",
        "publisher": "",
        "isbn": "",
        "dewey decimal call number": "",
        "contact": "",
        "subjects": "",
        "keywords": "",
        "length": "",
        "index": "book 1"
    }
]